qlar4rtss/__init__.py
qlar4rtss/extract_experiment_stats.py
qlar4rtss/feature_extract.py
qlar4rtss/model/feature_order.csv
qlar4rtss-0.1.0.dist-info/METADATA
qlar4rtss-0.1.0.dist-info/WHEEL
qlar4rtss-0.1.0.dist-info/top_level.txt
qlar4rtss-0.1.0.dist-info/RECORD
